hiddenfiles/__init__.py
hiddenfiles/create_symlinks.py
hiddenfiles/jobs/__init__.py
hiddenfiles/jobs/backup_retrieve.py
hiddenfiles/jobs/repos.py
hiddenfiles/jobs/setup_windows.py
hiddenfiles/jobs/utils.py
hiddenfiles/misc/__init__.py
hiddenfiles/misc/send2remote.py
hiddenfiles/misc/vars.py
hiddenfiles/windows_terminal_setup/__init__.py
hiddenfiles/windows_terminal_setup/change_terminal_settings.py
hiddenfiles/windows_terminal_setup/fancy_prompt_themes.py
hiddenfiles-0.0.4.dist-info/METADATA
hiddenfiles-0.0.4.dist-info/WHEEL
hiddenfiles-0.0.4.dist-info/top_level.txt
hiddenfiles-0.0.4.dist-info/RECORD
