Metadata-Version: 2.1
Name: hiddenfiles
Version: 0.0.4
Summary: Dotfiles management package
Home-page: https://github.com/thisismygitrepo/dofiles
Author: Alex Al-Saffar
Author-email: programmer@usa.com
Project-URL: Bug Tracker, https://github.com/thisismygitrepo/dofiles/issues
Classifier: Programming Language :: Python :: 3
Classifier: License :: OSI Approved :: MIT License
Classifier: Operating System :: OS Independent
Requires-Python: >=3.9
